aiplusiot/AiPlusIOT.py
aiplusiot/__init__.py
aiplusiot/actuators/Actuator.py
aiplusiot/actuators/Light.py
aiplusiot/actuators/LightFeatures.py
aiplusiot/actuators/__init__.py
aiplusiot/devices/Device.py
aiplusiot/devices/__init__.py
aiplusiot/image_processors/ImageProcessor.py
aiplusiot/image_processors/__init__.py
aiplusiot/sensors/Sensor.py
aiplusiot/sensors/__init__.py
aiplusiot/sensors/binary_sensors/BinarySensor.py
aiplusiot/sensors/binary_sensors/BinarySensorClasses.py
aiplusiot/sensors/binary_sensors/HeatSensor.py
aiplusiot/sensors/binary_sensors/IasZoneSensor.py
aiplusiot/sensors/binary_sensors/MotionSensor.py
aiplusiot/sensors/binary_sensors/OccupancySensor.py
aiplusiot/sensors/binary_sensors/OpeningSensor.py
aiplusiot/sensors/binary_sensors/ProblemSensor.py
aiplusiot/sensors/binary_sensors/SoundSensor.py
aiplusiot/sensors/binary_sensors/__init__.py
aiplusiot/sensors/standard_sensors/BatterySensor.py
aiplusiot/sensors/standard_sensors/CO2Sensor.py
aiplusiot/sensors/standard_sensors/CurrentSensor.py
aiplusiot/sensors/standard_sensors/HumiditySensor.py
aiplusiot/sensors/standard_sensors/IlluminanceSensor.py
aiplusiot/sensors/standard_sensors/NoiseSensor.py
aiplusiot/sensors/standard_sensors/ObjectsSensor.py
aiplusiot/sensors/standard_sensors/PressureSensor.py
aiplusiot/sensors/standard_sensors/SensorClasses.py
aiplusiot/sensors/standard_sensors/SignalStrengthSensor.py
aiplusiot/sensors/standard_sensors/StandardSensor.py
aiplusiot/sensors/standard_sensors/TemperatureSensor.py
aiplusiot/sensors/standard_sensors/__init__.py
aiplusiot/switches/Switch.py
aiplusiot/switches/__init__.py
aiplusiot-1.0.0.dist-info/LICENSE
aiplusiot-1.0.0.dist-info/METADATA
aiplusiot-1.0.0.dist-info/WHEEL
aiplusiot-1.0.0.dist-info/top_level.txt
aiplusiot-1.0.0.dist-info/RECORD
