Metadata-Version: 2.1
Name: aiplusiot
Version: 1.0.0
Summary: aiPlus IOT library
Home-page: UNKNOWN
Author: aiplus
License: UNKNOWN
Platform: UNKNOWN
Classifier: Programming Language :: Python :: 3
Classifier: License :: OSI Approved :: GNU General Public License v3 (GPLv3)
Classifier: Operating System :: OS Independent
Requires-Python: >=3.6
License-File: LICENSE
Requires-Dist: hass-client
